<annotation>
	<folder>Weed Detection</folder>
	<filename>IMG_8334.JPG</filename>
	<path>D:\Users\Colby\Desktop\Weed Detection\IMG_8334.JPG</path>
	<source>
		<database>Unknown</database>
	</source>
	<size>
		<width>5184</width>
		<height>3456</height>
		<depth>3</depth>
	</size>
	<segmented>0</segmented>
	<object>
		<name>Weed</name>
		<pose>Unspecified</pose>
		<truncated>0</truncated>
		<difficult>0</difficult>
		<bndbox>
			<xmin>1061</xmin>
			<ymin>2617</ymin>
			<xmax>1329</xmax>
			<ymax>2974</ymax>
		</bndbox>
	</object>
	<object>
		<name>Weed</name>
		<pose>Unspecified</pose>
		<truncated>0</truncated>
		<difficult>0</difficult>
		<bndbox>
			<xmin>1732</xmin>
			<ymin>453</ymin>
			<xmax>2504</xmax>
			<ymax>1217</ymax>
		</bndbox>
	</object>
	<object>
		<name>Weed</name>
		<pose>Unspecified</pose>
		<truncated>0</truncated>
		<difficult>0</difficult>
		<bndbox>
			<xmin>1357</xmin>
			<ymin>1164</ymin>
			<xmax>1711</xmax>
			<ymax>1471</ymax>
		</bndbox>
	</object>
	<object>
		<name>Weed</name>
		<pose>Unspecified</pose>
		<truncated>0</truncated>
		<difficult>0</difficult>
		<bndbox>
			<xmin>290</xmin>
			<ymin>571</ymin>
			<xmax>1322</xmax>
			<ymax>1414</ymax>
		</bndbox>
	</object>
	<object>
		<name>Weed</name>
		<pose>Unspecified</pose>
		<truncated>0</truncated>
		<difficult>0</difficult>
		<bndbox>
			<xmin>711</xmin>
			<ymin>10</ymin>
			<xmax>1050</xmax>
			<ymax>171</ymax>
		</bndbox>
	</object>
	<object>
		<name>Weed</name>
		<pose>Unspecified</pose>
		<truncated>0</truncated>
		<difficult>0</difficult>
		<bndbox>
			<xmin>2100</xmin>
			<ymin>81</ymin>
			<xmax>2432</xmax>
			<ymax>396</ymax>
		</bndbox>
	</object>
	<object>
		<name>Weed</name>
		<pose>Unspecified</pose>
		<truncated>0</truncated>
		<difficult>0</difficult>
		<bndbox>
			<xmin>3643</xmin>
			<ymin>10</ymin>
			<xmax>4075</xmax>
			<ymax>978</ymax>
		</bndbox>
	</object>
	<object>
		<name>Weed</name>
		<pose>Unspecified</pose>
		<truncated>0</truncated>
		<difficult>0</difficult>
		<bndbox>
			<xmin>3982</xmin>
			<ymin>1778</ymin>
			<xmax>4361</xmax>
			<ymax>2231</ymax>
		</bndbox>
	</object>
	<object>
		<name>Weed</name>
		<pose>Unspecified</pose>
		<truncated>0</truncated>
		<difficult>0</difficult>
		<bndbox>
			<xmin>3572</xmin>
			<ymin>2046</ymin>
			<xmax>3757</xmax>
			<ymax>2160</ymax>
		</bndbox>
	</object>
	<object>
		<name>Weed</name>
		<pose>Unspecified</pose>
		<truncated>1</truncated>
		<difficult>0</difficult>
		<bndbox>
			<xmin>4936</xmin>
			<ymin>824</ymin>
			<xmax>5184</xmax>
			<ymax>1644</ymax>
		</bndbox>
	</object>
</annotation>
